AUTHORS
ChangeLog
README.rst
requirements.txt
setup.cfg
setup.py
examples/activate_license.py
examples/expire_license.py
examples/list_licenses.py
examples/retrieve_license.py
manage2/__init__.py
manage2/resources/__init__.py
python_manage2.egg-info/PKG-INFO
python_manage2.egg-info/SOURCES.txt
python_manage2.egg-info/dependency_links.txt
python_manage2.egg-info/not-zip-safe
python_manage2.egg-info/requires.txt
python_manage2.egg-info/top_level.txt